pipster/__init__.py
pipster/_formatter.py
pipster/_version.py
pipster/install.py
pipster/_experimental/__init__.py
pipster/_experimental/autoinstall.py
pipster/_experimental/install_if_not_found.py
pipster-0.0.24.dist-info/METADATA
pipster-0.0.24.dist-info/WHEEL
pipster-0.0.24.dist-info/licenses/LICENSE
pipster-0.0.24.dist-info/RECORD
