Metadata-Version: 2.1
Name: pipster
Version: 0.0.24
Summary: pip install from inside your scripts
Project-URL: Homepage, https://github.com/reynoldsnlp/pipster
Project-URL: Bug Tracker, https://github.com/reynoldsnlp/pipster/issues
Author-email: Robert Reynolds <robert_reynolds@byu.edu>
License: Copyright (c) 2018-2019 The pipster developers (see pyproject.toml file)
License-File: LICENSE
Classifier: License :: OSI Approved :: GNU General Public License v3 (GPLv3)
Classifier: Operating System :: OS Independent
Classifier: Programming Language :: Python :: 3.8
Classifier: Programming Language :: Python :: 3.9
Classifier: Programming Language :: Python :: 3.10
Classifier: Programming Language :: Python :: 3.11
Classifier: Programming Language :: Python :: 3.12
Requires-Dist: pip
Provides-Extra: dev
Requires-Dist: black; extra == 'dev'
Requires-Dist: mypy; extra == 'dev'
Requires-Dist: pytest-cov>=4.0; extra == 'dev'
Requires-Dist: pytest>=6.0; extra == 'dev'
Requires-Dist: ruff; extra == 'dev'
Provides-Extra: lint
Requires-Dist: black; extra == 'lint'
Requires-Dist: mypy; extra == 'lint'
Requires-Dist: ruff; extra == 'lint'
Provides-Extra: test
Requires-Dist: pytest-cov>=4.0; extra == 'test'
Requires-Dist: pytest>=6.0; extra == 'test'
